MANIFEST.in
README.md
setup.cfg
setup.py
topsis_kritika_101983031/__init__.py
topsis_kritika_101983031/assign6.py
topsis_kritika_101983031.egg-info/PKG-INFO
topsis_kritika_101983031.egg-info/SOURCES.txt
topsis_kritika_101983031.egg-info/dependency_links.txt
topsis_kritika_101983031.egg-info/requires.txt
topsis_kritika_101983031.egg-info/top_level.txt