Metadata-Version: 2.1
Name: topsis-kritika-101983031
Version: 1.0
Summary: python implementation for TOPSIS
Home-page: https://github.com/kritsid/TOPSIS-kritika-101983031
Author: kritika aggarwal
Author-email: kritikaaggarwal1621@gmail.com
License: UNKNOWN
Platform: UNKNOWN
Classifier: Programming Language :: Python :: 3
Classifier: License :: OSI Approved :: MIT License
Classifier: Operating System :: OS Independent
